jllama/__init__.py
jllama/config.py
jllama/env.py
jllama/logging.conf
jllama/main.py
jllama/nav.json
jllama/ai/__init__.py
jllama/ai/base_reasoning.py
jllama/ai/llama_reasoning.py
jllama/ai/llama_server.py
jllama/ai/llamafactory_server.py
jllama/ai/model_finetuning.py
jllama/ai/reasoning_service.py
jllama/ai/sd_ip_adapter_faceid.py
jllama/ai/sd_reasoning.py
jllama/ai/transformers_reasoning.py
jllama/controller/__init__.py
jllama/controller/api.py
jllama/ext/__init__.py
jllama/ext/convert_hf_to_gguf.py
jllama/ext/convert_hf_to_gguf_update.py
jllama/ext/convert_llama_ggml_to_gguf.py
jllama/ext/convert_lora_to_gguf.py
jllama/ext/gguf_py/__init__.py
jllama/ext/gguf_py/gguf/__init__.py
jllama/ext/gguf_py/gguf/constants.py
jllama/ext/gguf_py/gguf/gguf.py
jllama/ext/gguf_py/gguf/gguf_reader.py
jllama/ext/gguf_py/gguf/gguf_writer.py
jllama/ext/gguf_py/gguf/lazy.py
jllama/ext/gguf_py/gguf/metadata.py
jllama/ext/gguf_py/gguf/py.typed
jllama/ext/gguf_py/gguf/quants.py
jllama/ext/gguf_py/gguf/tensor_mapping.py
jllama/ext/gguf_py/gguf/utility.py
jllama/ext/gguf_py/gguf/vocab.py
jllama/ext/gguf_py/tests/__init__.py
jllama/ext/gguf_py/tests/test_metadata.py
jllama/ext/gguf_py/tests/test_quants.py
jllama/ext/llama_cpp/LICENSE-curl
jllama/ext/llama_cpp/LICENSE-httplib
jllama/ext/llama_cpp/LICENSE-jsonhpp
jllama/ext/llama_cpp/LICENSE-linenoise
jllama/ext/llama_cpp/ggml-base.dll
jllama/ext/llama_cpp/ggml-cpu-alderlake.dll
jllama/ext/llama_cpp/ggml-cpu-haswell.dll
jllama/ext/llama_cpp/ggml-cpu-icelake.dll
jllama/ext/llama_cpp/ggml-cpu-sandybridge.dll
jllama/ext/llama_cpp/ggml-cpu-sapphirerapids.dll
jllama/ext/llama_cpp/ggml-cpu-skylakex.dll
jllama/ext/llama_cpp/ggml-cpu-sse42.dll
jllama/ext/llama_cpp/ggml-cpu-x64.dll
jllama/ext/llama_cpp/ggml-rpc.dll
jllama/ext/llama_cpp/ggml.dll
jllama/ext/llama_cpp/libcurl-x64.dll
jllama/ext/llama_cpp/libomp140.x86_64.dll
jllama/ext/llama_cpp/llama-batched-bench.exe
jllama/ext/llama_cpp/llama-bench.exe
jllama/ext/llama_cpp/llama-cli.exe
jllama_py-1.1.11.dist-info/licenses/LICENSE
jllama_py-1.1.11.dist-info/METADATA
jllama_py-1.1.11.dist-info/WHEEL
jllama_py-1.1.11.dist-info/entry_points.txt
jllama_py-1.1.11.dist-info/top_level.txt
jllama_py-1.1.11.dist-info/RECORD
