Metadata-Version: 2.4
Name: jllama-py
Version: 1.1.11
Summary: A simple AI Tool set application
Home-page: https://github.com/zjwan461/jllama-py
Author: Jerry
Author-email: 826935261@qq.com
License: MIT
Keywords: gguf AI huggingface modelscope pytorch transformers llama_cpp llamafactory
Classifier: License :: OSI Approved :: MIT License
Classifier: Operating System :: Microsoft :: Windows
Classifier: Programming Language :: Python :: 3.11
Requires-Python: >=3.11
License-File: LICENSE
Requires-Dist: pywebview==5.4
Requires-Dist: flask==3.1.1
Requires-Dist: flask-cors==6.0.1
Requires-Dist: requests==2.32.3
Requires-Dist: psutil==7.0.0
Requires-Dist: GPUtil==1.4.0
Requires-Dist: SQLAlchemy==2.0.41
Requires-Dist: modelscope==1.26.0
Requires-Dist: orjson==3.10.18
Requires-Dist: transformers==4.52.4; sys_platform != "darwin"
Requires-Dist: accelerate==1.7.0
Requires-Dist: addict==2.4.0
Requires-Dist: WMI==1.5.1; sys_platform == "win32"
Requires-Dist: hf_xet==1.1.5
Requires-Dist: torch~=2.7.1
Requires-Dist: numpy~=1.26.4
Requires-Dist: tqdm~=4.67.1
Requires-Dist: sentencepiece~=0.2.0
Requires-Dist: pyyaml~=6.0.2
Requires-Dist: huggingface-hub~=0.33.0
Requires-Dist: uvicorn~=0.34.3
Requires-Dist: datasets~=3.6.0
Requires-Dist: bitsandbytes~=0.46.0
Requires-Dist: peft~=0.15.2
Requires-Dist: safetensors~=0.5.3
Requires-Dist: jinja2~=3.1.6
Requires-Dist: paramiko~=3.5.1
Requires-Dist: scp~=0.15.0
Requires-Dist: llamafactory==0.9.3
Requires-Dist: llama-cpp-python[server]~=0.3.2
Requires-Dist: matplotlib~=3.10.3
Requires-Dist: diffusers~=0.34.0
Requires-Dist: pillow~=11.3.0
Requires-Dist: transformers~=4.52.4
Requires-Dist: setuptools~=78.1.1
Requires-Dist: insightface~=0.7.3
Requires-Dist: ip_adapterv~=0.1.0
Requires-Dist: onnxruntime~=1.22.1
Dynamic: author
Dynamic: author-email
Dynamic: classifier
Dynamic: description
Dynamic: description-content-type
Dynamic: home-page
Dynamic: keywords
Dynamic: license
Dynamic: license-file
Dynamic: requires-dist
Dynamic: requires-python
Dynamic: summary
